license.txt
publish.py
readme.md
screenshot.jpg
setup.py
trezor_gpg_pinentry_tk.py
trezor_gpg_pinentry_tk.egg-info/PKG-INFO
trezor_gpg_pinentry_tk.egg-info/SOURCES.txt
trezor_gpg_pinentry_tk.egg-info/dependency_links.txt
trezor_gpg_pinentry_tk.egg-info/entry_points.txt
trezor_gpg_pinentry_tk.egg-info/top_level.txt