Metadata-Version: 1.1
Name: trezor-gpg-pinentry-tk
Version: 0.0.10
Summary: A pinentry for GPG with Trezor
Home-page: https://gitlab.com/rendaw/trezor-gpg-pinentry-tk
Author: rendaw
Author-email: spoo@zarbosoft.com
License: BSD
Download-URL: https://gitlab.com/rendaw/trezor-gpg-pinentry-tk/tarball/v0.0.10
Platform: UNKNOWN
Classifier: License :: OSI Approved :: BSD License
